MANIFEST.in
README.md
setup.py
evtcantools/__init__.py
evtcantools/dbcmaker.py
evtcantools/dbcparser.py
evtcantools.egg-info/PKG-INFO
evtcantools.egg-info/SOURCES.txt
evtcantools.egg-info/dependency_links.txt
evtcantools.egg-info/not-zip-safe
evtcantools.egg-info/top_level.txt
evtcantools/dbcfolder/IEC.dbc
tests/__init__.py