Metadata-Version: 1.0
Name: evtcantools
Version: 0.1.3
Summary: Tools shared across EVT software projects
Home-page: https://bitbucket.org/evt/evt-can-tools
Author: EVT RIT
Author-email: evt@rit.edu
License: MIT
Platform: UNKNOWN
